pycm/__init__.py
pycm/cli.py
pycm/core.py
pycm/secrets.py
pycm/utils.py
python_configuration_management-4.0.0.dist-info/entry_points.txt
python_configuration_management-4.0.0.dist-info/LICENSE
python_configuration_management-4.0.0.dist-info/WHEEL
python_configuration_management-4.0.0.dist-info/METADATA
python_configuration_management-4.0.0.dist-info/RECORD
