Metadata-Version: 2.1
Name: python-configuration-management
Version: 4.0.0
Summary: A merge conflict-less solution to committing an encrypted configuration to the repo with secrets and non-secrets side-by-side.
Home-page: https://github.com/Kicksaw-Consulting/python-configuration-management
License: MIT
Keywords: config,secrets,settings
Author: Alex Drozd
Author-email: alex@kicksaw.com
Requires-Python: >=3.8,<4.0
Classifier: License :: OSI Approved :: MIT License
Classifier: Programming Language :: Python :: 3
Classifier: Programming Language :: Python :: 3.10
Classifier: Programming Language :: Python :: 3.8
Classifier: Programming Language :: Python :: 3.9
Requires-Dist: cryptography (>=3.3.1,<4.0.0)
Requires-Dist: python-dotenv (>=0.15.0,<0.16.0)
Requires-Dist: pyyaml (>=5.3.1,<6.0.0)
Project-URL: Repository, https://github.com/Kicksaw-Consulting/python-configuration-management
